{
  "slug": "reverse-linked-list",
  "title": "Reverse Linked List",
  "description": "Solve the **Reverse Linked List** problem.\n\nSee the full problem description on [LeetCode](https://leetcode.com/problems/reverse-linked-list/).",
  "examples": [
    {
      "input": "head = [1,2,3,4,5]",
      "output": "[5,4,3,2,1]"
    },
    {
      "input": "head = [1,2]",
      "output": "[2,1]"
    },
    {
      "input": "head = [1]",
      "output": "[1]"
    }
  ],
  "constraints": [],
  "function": {
    "name": "reverseList",
    "params": [
      {
        "name": "head",
        "type": "ListNode"
      }
    ],
    "returnType": "ListNode"
  },
  "testCases": [
    {
      "input": {
        "head": [
          1,
          2,
          3,
          4,
          5
        ]
      },
      "expected": [
        5,
        4,
        3,
        2,
        1
      ]
    },
    {
      "input": {
        "head": [
          1,
          2
        ]
      },
      "expected": [
        2,
        1
      ]
    },
    {
      "input": {
        "head": []
      },
      "expected": []
    },
    {
      "input": {
        "head": [
          1
        ]
      },
      "expected": [
        1
      ]
    }
  ],
  "starterCode": {
    "javascript": "/**\n * @param {ListNode} head\n * @return {ListNode}\n */\nfunction reverseList(head) {\n  // Write your solution here\n}",
    "typescript": "function reverseList(head: ListNode | null): ListNode | null {\n  // Write your solution here\n}",
    "python": "def reverse_list(head: Optional[ListNode]) -> Optional[ListNode]:\n    # Write your solution here\n    pass",
    "cpp": "ListNode* reverseList(ListNode* head) {\n    // Write your solution here\n}",
    "go": "func reverseList(head *ListNode) *ListNode {\n    // Write your solution here\n}"
  },
  "functionNameMap": {
    "javascript": "reverseList",
    "typescript": "reverseList",
    "python": "reverse_list",
    "cpp": "reverseList",
    "go": "ReverseList"
  }
}
